todolist_angrypig555/__init__.py
todolist_angrypig555/__main__.py
todolist_angrypig555/light.tcss
todolist_angrypig555/main.py
todolist_angrypig555/main.tcss
todolist_angrypig555-1.1.1.dist-info/licenses/LICENSE
todolist_angrypig555-1.1.1.dist-info/METADATA
todolist_angrypig555-1.1.1.dist-info/WHEEL
todolist_angrypig555-1.1.1.dist-info/top_level.txt
todolist_angrypig555-1.1.1.dist-info/RECORD
