Metadata-Version: 2.4
Name: todolist_angrypig555
Version: 1.1.1
Summary: A todolist made with the textual library with the ability to open and save your todo-list
Author: angrypig555
License-Expression: MIT
Project-URL: Homepage, https://github.com/angrypig555/to-do-list
Project-URL: Issues, https://github.com/angrypig555/to-do-list/issues
Classifier: Programming Language :: Python :: 3
Classifier: Operating System :: OS Independent
Requires-Python: >=3.9
License-File: LICENSE
Requires-Dist: textual
Dynamic: license-file
